LICENSE
README.md
setup.py
pyims/__init__.py
pyims/forcast.py
pyims/pyims.py
pyims/radarsatellite.py
pyims/weather.py
python_ims.egg-info/PKG-INFO
python_ims.egg-info/SOURCES.txt
python_ims.egg-info/dependency_links.txt
python_ims.egg-info/requires.txt
python_ims.egg-info/top_level.txt